setup.cfg
setup.py
clira/__init__.py
clira/cli.py
clira/utils.py
clira.egg-info/PKG-INFO
clira.egg-info/SOURCES.txt
clira.egg-info/dependency_links.txt
clira.egg-info/entry_points.txt
clira.egg-info/requires.txt
clira.egg-info/top_level.txt
clira/commands/__init__.py
clira/commands/history.py
clira/commands/time_report.py