Metadata-Version: 1.1
Name: clira
Version: 0.1.7
Summary: Command line client for Jira
Home-page: https://gitlab.com/havk/clira
Author: Paweł Jastrzębski
Author-email: jastrzab5@gmail.com
License: UNKNOWN
Download-URL: https://gitlab.com/havk/clira/repository/archive.tar.gz?ref=0.1.4
Keywords: JIRA,jira,terminal,cli
Platform: UNKNOWN
